trio_bybit/__init__.py
trio_bybit/client.py
trio_bybit/enums.py
trio_bybit/exceptions.py
trio_bybit/helpers.py
trio_bybit/streams.py
trio_bybit-0.3.8.dist-info/METADATA
trio_bybit-0.3.8.dist-info/WHEEL
trio_bybit-0.3.8.dist-info/licenses/LICENSE
trio_bybit-0.3.8.dist-info/RECORD
