Metadata-Version: 2.3
Name: trio-bybit
Version: 0.3.8
Summary: Python bybit async SDK based on trio.
Project-URL: Repository, https://github.com/halfelf/trio-bybit
Author-email: Shu Wang <halfelf.ronin@gmail.com>
License: MIT License
License-File: LICENSE
Keywords: bybit,crypto
Classifier: Development Status :: 4 - Beta
Classifier: Intended Audience :: Developers
Classifier: License :: OSI Approved :: MIT License
Classifier: Programming Language :: Python :: 3.12
Classifier: Topic :: Software Development :: Libraries
Requires-Python: >=3.12
Requires-Dist: cryptography>=42.0.7
Requires-Dist: dateparser>=1.2.0
Requires-Dist: httpx[http2]>=0.27.0
Requires-Dist: orjson>=3.10.3
Requires-Dist: pytz>=2024.1
Requires-Dist: trio-util>=0.7.0
Requires-Dist: trio-websocket>=0.11.1
Requires-Dist: trio>=0.25.1
